aerarium/__init__.py
aerarium/accounts.py
aerarium/consts.py
aerarium/stats.py
aerarium/utils.py
aerarium-1.0.0.data/scripts/aerarium
scripts/__init__.py
aerarium-1.0.0.dist-info/LICENSE
aerarium-1.0.0.dist-info/METADATA
aerarium-1.0.0.dist-info/WHEEL
aerarium-1.0.0.dist-info/top_level.txt
aerarium-1.0.0.dist-info/RECORD
