Metadata-Version: 2.1
Name: aerarium
Version: 1.0.0
Summary: A CLI tool to track finances
Home-page: https://github.com/virajsazzala/aerarium
Author: SNG Viraj Reddy
Author-email: vir200319@gmail.com
License: MIT
Platform: UNKNOWN
Classifier: Development Status :: 3 - Alpha
Classifier: Intended Audience :: Developers
Classifier: License :: OSI Approved :: MIT License
Classifier: Programming Language :: Python :: 3
Classifier: Programming Language :: Python :: 3.6
Classifier: Programming Language :: Python :: 3.7
Classifier: Programming Language :: Python :: 3.8
License-File: LICENSE
Requires-Dist: PyYAML
Requires-Dist: colorama
Requires-Dist: pandas
Requires-Dist: scikit-learn
Requires-Dist: tabulate
